lua_table.py
lua_table-0.4.2.dist-info/COPYING
lua_table-0.4.2.dist-info/METADATA
lua_table-0.4.2.dist-info/WHEEL
lua_table-0.4.2.dist-info/top_level.txt
lua_table-0.4.2.dist-info/RECORD
