Metadata-Version: 2.2
Name: lua_table
Version: 0.4.2
Summary: Parser of the serialized Lua tables
Author: Matěj Cepl
Author-email: mcepl@cepl.eu
Project-URL: source, https://git.sr.ht/~mcepl/lua_table
Project-URL: report, https://lists.sr.ht/~mcepl/devel
Keywords: Lua
Classifier: Programming Language :: Python
Classifier: Programming Language :: Python :: Implementation :: PyPy
Classifier: Programming Language :: Python :: 3
Classifier: Development Status :: 4 - Beta
Classifier: Intended Audience :: Developers
Classifier: License :: OSI Approved :: GNU Lesser General Public License v3 (LGPLv3)
Classifier: Operating System :: OS Independent
Classifier: Topic :: Software Development :: Libraries :: Python Modules
License-File: COPYING
Requires-Dist: rply
